Trees/AVLTree.py
Trees/BST.py
Trees/BinaryTree.py
Trees/Heap.py
cs46_abundanceoftrees-3.0.3.dist-info/DESCRIPTION.rst
cs46_abundanceoftrees-3.0.3.dist-info/METADATA
cs46_abundanceoftrees-3.0.3.dist-info/RECORD
cs46_abundanceoftrees-3.0.3.dist-info/WHEEL
cs46_abundanceoftrees-3.0.3.dist-info/entry_points.txt
cs46_abundanceoftrees-3.0.3.dist-info/metadata.json
cs46_abundanceoftrees-3.0.3.dist-info/top_level.txt
