Metadata-Version: 2.0
Name: cs46-abundanceoftrees
Version: 3.0.3
Summary: Implementation of Binary Tree, AVL Tree and Heap Tree Data Structures
Home-page: https://github.com/ma-alvarado/trees
Author: Matías Alvarado
Author-email: matias@4alvarados.com
License: GPLv3
Platform: UNKNOWN
Classifier: Programming Language :: Python :: 3
Classifier: Programming Language :: Python :: 3.7
Requires-Dist: hypothesis
Requires-Dist: pytest
